{"description":"Test Angularjs app|This is new test","passed":true,"pending":false,"os":"Windows NT","sessionId":"0eee573f7e891b4c5b5c6b7abcfca037","instanceId":11868,"browser":{"name":"chrome","version":"74.0.3729.169"},"message":"Passed","browserLogs":[{"level":"WARNING","message":"deprecation - HTML Imports is deprecated and will be removed in M73, around March 2019. Please use ES modules instead. See https://www.chromestatus.com/features/5144752345317376 for more details.","timestamp":1559674617310,"type":""}],"screenShotFile":"00e30023-0056-00e1-0010-006d0010004e.png","timestamp":1559674628059,"duration":8487}
